{
  "products": [
    {
      "superSku": "SuperSKU1",
      "title": "Модель сетевого шуруповерта от Днепр-М МДШ-600 – практичный и доступный инструмент, отличающийся своей функциональностью и простотой в обращении.",
      "attributes": [
        {
          "title": "Напряжение",
          "value": "220 В"
        }
      ],
      "description": "Благодаря специальной системе регулировки степени вкручивания самореза легко работать с мягкими материалами (гипсокартон, пластик) без риска их повреждения. Оснастку заменить стало еще проще, так как патрон зажимается без дополнительных инструментов. В модели МДШ-600 реализована функция реверса с помощью кнопки, что позволяет менять направление вращения по необходимости.",
      "defaultSku": "sku1",
      "simpleProducts": {
        "sku1": {
          "parentSuperSku": "SuperSKU1",
          "title": "Qwe",
          "price": "124",
          "sku": "69091000",
          "images": {
            "0": {
              "title": "Qwe",
              "alt": "Сетевой шуруповерт Дніпро-М",
              "src": "https://vaiyav.github.io/sites/motive/img/content/pic1.jpg"
            }
          }
        }
      }
    },
    {
      "superSku": "SuperSKU2",
      "title": "Аккумуляторный шуруповерт Intertool DT-0310 характеризуется наличием быстрозажимного патрона 1-10 мм, высоким крутящим моментом, NiCd батареей, которую можно будет зарядить до полной готовности за 3 часа, возможностью сверления отверстий в дереве и металле.",
      "attributes": [
        {
          "title": "Скорость вращения",
          "value": "750 об/мин"
        }
      ],
      "description": "Кнопка-ползунок реверса расположена таким образом, что ее невозможно случайным образом зацепить, а переключать очень удобно. Качество внутреннего исполнения инструмента находится на высоком уровне: элементы двигателя обрабатываются термостойким лаком, защищающим инструмент от перегревов и снижающий общий механический износ. Кроме того, подшипники имеют прорезиненную прокладку, которая предотвращает попадание пыли из внешней среды, опорный подшипник стабилизируется каучуковой втулкой. Спектр применения шуруповерта обширен, поэтому он станет отличным приобретением по доступной цене для требовательного хозяина.",
      "defaultSku": "sku2",
      "simpleProducts": {
        "sku2": {
          "parentSuperSku": "SuperSKU2",
          "title": "Rty",
          "price": "384",
          "sku": "69091002",
          "images": {
            "0": {
              "title": "Сетевой шуруповерт Дніпро-М",
              "alt": "Сетевой шуруповерт Дніпро-М",
              "src": "https://vaiyav.github.io/sites/motive/img/content/pic2.jpg"
            }
          }
        }
      }
    },
    {
      "superSku": "SuperSKU3",
      "title": "Сетевой шуруповерт ТехАС ТА-01-104 применяется для монтажных работ и сверления в различных материалах.",
      "attributes": [
        {
          "title": "Вес",
          "value": "1.3 кг"
        }
      ],
      "description": "Такой инструмент в руках настоящего профессионала может выполнить большой объем работы по сверлению, вкручиванию и выкручиванию элементов крепления. Шуруповерты нашли широкое применение, как в быту, так и на производствах. Такой инструмент значительно экономит время по работе с саморезами и шурупами. Кроме функций вкручивания/выкручивания, шуруповертом DT-0310 возможно работать и в качестве дрели для сверления отверстий небольшого диаметра.",
      "defaultSku": "sku3",
      "simpleProducts": {
        "sku3": {
          "parentSuperSku": "SuperSKU3",
          "title": "Сетевой шуруповерт Дніпро-М МДШ-600",
          "price": "284",
          "sku": "69091003",
          "images": {
            "0": {
              "title": "Сетевой шуруповерт Дніпро-М",
              "alt": "Сетевой шуруповерт Дніпро-М",
              "src": "https://vaiyav.github.io/sites/motive/img/content/pic3.jpg"
            }
          }
        }
      }
    }
  ],
  "feedbacks": [],
  "orders": [
    {
      "order": {
        "name": "Qwetr",
        "email": "",
        "payment": {
          "title": "Безналичный",
          "value": "nonCash"
        },
        "confirm": false,
        "address": "qwe",
        "delivery": {
          "title": "Самовывоз",
          "value": "personally"
        },
        "text": "",
        "statusPayment": "Не оплачено",
        "items": [
          {
            "superSku": "SuperSKU3",
            "title": "Сетевой шуруповерт ТехАС ТА-01-104 применяется для монтажных работ и сверления в различных материалах.",
            "attributes": [
              {
                "title": "Вес",
                "value": "1.3 кг"
              }
            ],
            "description": "Такой инструмент в руках настоящего профессионала может выполнить большой объем работы по сверлению, вкручиванию и выкручиванию элементов крепления. Шуруповерты нашли широкое применение, как в быту, так и на производствах. Такой инструмент значительно экономит время по работе с саморезами и шурупами. Кроме функций вкручивания/выкручивания, шуруповертом DT-0310 возможно работать и в качестве дрели для сверления отверстий небольшого диаметра.",
            "defaultSku": "sku3",
            "simpleProducts": {
              "sku3": {
                "parentSuperSku": "SuperSKU3",
                "title": "Сетевой шуруповерт Дніпро-М МДШ-600",
                "price": "284",
                "sku": "69091003",
                "images": {
                  "0": {
                    "title": "Сетевой шуруповерт Дніпро-М",
                    "alt": "Сетевой шуруповерт Дніпро-М",
                    "src": "https://vaiyav.github.io/sites/motive/img/content/pic3.jpg"
                  }
                }
              }
            },
            "count": 3
          }
        ]
      },
      "id": 1
    }
  ]
}